Metadata-Version: 2.1
Name: image-dataset-converter-imgstats
Version: 0.0.2
Summary: Image statistics extension for the image-dataset-converter library.
Home-page: https://github.com/waikato-datamining/image-dataset-converter-imgstats
Author: Peter Reutemann
Author-email: fracpete@waikato.ac.nz
License: MIT License
Classifier: Development Status :: 4 - Beta
Classifier: License :: OSI Approved :: MIT License
Classifier: Topic :: Scientific/Engineering :: Artificial Intelligence
Classifier: Topic :: Scientific/Engineering :: Image Processing
License-File: LICENSE
